pytest_codspeed/__init__.py
pytest_codspeed/config.py
pytest_codspeed/plugin.py
pytest_codspeed/py.typed
pytest_codspeed/utils.py
pytest_codspeed/instruments/__init__.py
pytest_codspeed/instruments/valgrind.py
pytest_codspeed/instruments/walltime.py
pytest_codspeed/instruments/hooks/__init__.py
pytest_codspeed/instruments/hooks/build.py
pytest_codspeed/instruments/hooks/dist_instrument_hooks.pyi
pytest_codspeed/instruments/hooks/instrument-hooks/dist/core.c
pytest_codspeed/instruments/hooks/instrument-hooks/includes/callgrind.h
pytest_codspeed/instruments/hooks/instrument-hooks/includes/core.h
pytest_codspeed/instruments/hooks/instrument-hooks/includes/valgrind.h
pytest_codspeed/instruments/hooks/instrument-hooks/includes/zig.h
pytest_codspeed/instruments/hooks/instrument-hooks/scripts/release.py
pytest_codspeed-4.1.1.dist-info/METADATA
pytest_codspeed-4.1.1.dist-info/WHEEL
pytest_codspeed-4.1.1.dist-info/entry_points.txt
pytest_codspeed-4.1.1.dist-info/top_level.txt
pytest_codspeed-4.1.1.dist-info/RECORD
