Metadata-Version: 2.4
Name: pytest-codspeed
Version: 4.1.1
Summary: Pytest plugin to create CodSpeed benchmarks
Author-email: Arthur Pastel <arthur@codspeed.io>
License: The MIT License (MIT)
Project-URL: Homepage, https://codspeed.io/
Project-URL: Documentation, https://codspeed.io/docs/reference/pytest-codspeed
Project-URL: Source, https://github.com/CodSpeedHQ/pytest-codspeed
Keywords: codspeed,benchmark,performance,pytest
Classifier: Development Status :: 5 - Production/Stable
Classifier: Framework :: Pytest
Classifier: Intended Audience :: Developers
Classifier: Intended Audience :: Information Technology
Classifier: License :: OSI Approved :: MIT License
Classifier: Programming Language :: Python :: 3
Classifier: Programming Language :: Python :: 3.9
Classifier: Programming Language :: Python :: 3.10
Classifier: Programming Language :: Python :: 3.11
Classifier: Programming Language :: Python :: 3.12
Classifier: Programming Language :: Python :: 3.13
Classifier: Topic :: Software Development :: Testing
Classifier: Topic :: System :: Benchmark
Classifier: Topic :: Utilities
Classifier: Typing :: Typed
Requires-Python: >=3.9
Requires-Dist: cffi>=1.17.1
Requires-Dist: pytest>=3.8
Requires-Dist: rich>=13.8.1
Requires-Dist: importlib-metadata>=8.5.0; python_version < "3.10"
Provides-Extra: compat
Requires-Dist: pytest-benchmark~=5.0.0; extra == "compat"
Requires-Dist: pytest-xdist~=3.6.1; extra == "compat"
